actedu_crawler/__init__.py
actedu_crawler/__main__.py
actedu_crawler-1.0.0.dist-info/METADATA
actedu_crawler-1.0.0.dist-info/WHEEL
actedu_crawler-1.0.0.dist-info/top_level.txt
actedu_crawler-1.0.0.dist-info/RECORD
