Metadata-Version: 2.1
Name: actedu-crawler
Version: 1.0.0
Summary: Crawl ACT Education websites' searchable documents for archival purposes.
Home-page: https://github.com/king-millez/actedu-crawler
Author: king-millez
Author-email: millez.dev@gmail.com
License: UNKNOWN
Platform: UNKNOWN
Classifier: Programming Language :: Python :: 3
Classifier: Operating System :: OS Independent
Requires-Python: >=3.6
